idocker/__init__.py
idocker/cli/__init__.py
idocker/cli/main.py
idocker-1.5.0.dist-info/LICENSE
idocker-1.5.0.dist-info/METADATA
idocker-1.5.0.dist-info/WHEEL
idocker-1.5.0.dist-info/entry_points.txt
idocker-1.5.0.dist-info/top_level.txt
idocker-1.5.0.dist-info/RECORD
